vindaloo/__init__.py
vindaloo/convert.py
vindaloo/examples.py
vindaloo/objects.py
vindaloo/utils.py
vindaloo/vindaloo.py
vindaloo-4.5.0.dist-info/METADATA
vindaloo-4.5.0.dist-info/WHEEL
vindaloo-4.5.0.dist-info/entry_points.txt
vindaloo-4.5.0.dist-info/top_level.txt
vindaloo-4.5.0.dist-info/RECORD
