Metadata-Version: 2.4
Name: vindaloo
Version: 4.5.0
Summary: K8S deployer
Home-page: https://github.com/seznam/vindaloo
Author: Daniel Milde
Author-email: daniel.milde@firma.seznam.cz
Classifier: Programming Language :: Python :: 3
Requires-Python: >=3.6
Requires-Dist: argcomplete>=1.9.5
Requires-Dist: chevron
Dynamic: author
Dynamic: author-email
Dynamic: classifier
Dynamic: description
Dynamic: description-content-type
Dynamic: home-page
Dynamic: requires-dist
Dynamic: requires-python
Dynamic: summary
